openthechests/__init__.py
openthechests/src/OpenTheChests.py
openthechests/src/OpenTheChestsGym.py
openthechests/src/__init__.py
openthechests/src/elements/Event.py
openthechests/src/elements/Generator.py
openthechests/src/elements/InteractiveBox.py
openthechests/src/elements/Parser.py
openthechests/src/elements/Pattern.py
openthechests/src/elements/__init__.py
openthechests/src/utils/__init__.py
openthechests/src/utils/allen.py
openthechests/src/utils/evaluators.py
openthechests/src/utils/helper_functions.py
openthechests/src/utils/modified_plotting.py
openthechests-0.5.8.dist-info/LICENSE
openthechests-0.5.8.dist-info/METADATA
openthechests-0.5.8.dist-info/WHEEL
openthechests-0.5.8.dist-info/top_level.txt
openthechests-0.5.8.dist-info/RECORD
