Metadata-Version: 2.1
Name: openthechests
Version: 0.5.8
Summary: Training environment for reinforcement learning with event-based context
Author-email: Nicolas Museux <nicolas.museux@thalesgroup.com>, Ivelina Stoyanova <ivelina.stoyanova@thalesgroup.com>
License: BSD 3-clauses
Project-URL: Homepage, https://github.com/ThalesGroup/open-the-chests
Project-URL: Bug Tracker, https://github.com/ThalesGroup/open-the-chests/issues
Project-URL: Repository, https://github.com/ThalesGroup/open-the-chests.git
Classifier: Programming Language :: Python :: 3
Classifier: License :: OSI Approved :: BSD License
Classifier: Operating System :: OS Independent
Requires-Python: >=3.9
License-File: LICENSE
Requires-Dist: gym >=0.21.0
Requires-Dist: numpy >=1.23.3
Requires-Dist: PyYAML >=6.0
Requires-Dist: plotly >=5.10.0
Requires-Dist: pandas >=1.5.0
Requires-Dist: matplotlib >=3.6.0
Requires-Dist: stable-baselines3 >=1.6.0
